smqtk_core/__init__.py
smqtk_core/configuration.py
smqtk_core/dict.py
smqtk_core/plugin.py
smqtk_core/py.typed
smqtk_core-0.20.0.dist-info/LICENSE.txt
smqtk_core-0.20.0.dist-info/METADATA
smqtk_core-0.20.0.dist-info/WHEEL
smqtk_core-0.20.0.dist-info/RECORD
