Metadata-Version: 2.1
Name: smqtk-core
Version: 0.20.0
Summary: Python toolkit for pluggable algorithms and data structures for multimedia-based machine learning.
Home-page: https://github.com/Kitware/SMQTK-Core
License: BSD-3-Clause
Author: Kitware, Inc.
Author-email: smqtk-developers@kitware.com
Requires-Python: >=3.10,<4.0
Classifier: Development Status :: 3 - Alpha
Classifier: Intended Audience :: Developers
Classifier: Intended Audience :: Science/Research
Classifier: License :: OSI Approved :: BSD License
Classifier: Operating System :: MacOS :: MacOS X
Classifier: Operating System :: Unix
Classifier: Programming Language :: Python :: 3
Classifier: Programming Language :: Python :: 3.10
Classifier: Programming Language :: Python :: 3.11
Classifier: Programming Language :: Python :: 3.12
Classifier: Programming Language :: Python :: 3.13
Project-URL: Documentation, https://smqtk-core.readthedocs.io/
Project-URL: Repository, https://github.com/Kitware/SMQTK-Core
